wsinfo/__init__.py
wsinfo-1.3.0.dist-info/DESCRIPTION.rst
wsinfo-1.3.0.dist-info/METADATA
wsinfo-1.3.0.dist-info/RECORD
wsinfo-1.3.0.dist-info/WHEEL
wsinfo-1.3.0.dist-info/metadata.json
wsinfo-1.3.0.dist-info/top_level.txt
